<odoo>
    <template id="mcm_website_theme.mcm_template_felicitations" name="Inscription avec succes | MCM">
        <t t-call="website.layout">
            <link href="/mcm_website_theme/static/src/css/felicitations.css" rel="stylesheet"></link>
            <!-- <div id="wrap" class="oe_structure oe_empty">
                <div class="js-container-animation container-animation">
                    <div class="container ">
                        <div class="checkmark-circle">
                            <div class="background"></div>
                            <div class="checkmark draw"></div>
                        </div>
                        <h1>Congratulations!</h1>
                        <p>You are all set. Well done!</p>
                        <button class="submit-btn" type="submit" onclick="alert('🥺🥺🥺🥺🥺\n Oh no you didn\'t!!!!!!!');">Continue</button>
                    </div>

                </div>


            </div> -->
            <div id="wrap" class="oe_structure oe_empty" data-oe-model="ir.ui.view" data-oe-id="11814" data-oe-field="arch" data-oe-xpath="/t[1]/t[1]/div[1]">
                <div class="js-container-animation container-animation">
                    <div class="" style="
                        /* width: max-content; */
                        height: 90vh;
                        position:absolute;
                        left:0;
                        right:0;
                        top:0;
                        bottom:0;
                        margin:auto;
                        max-width:100%;
                        max-height: 52vh;
                        text-align: center;
                        overflow:auto;
                        z-index: 2;
                    ">
                        <div class="checkmark-circle">
                            <div class="background"></div>
                            <div class="checkmark draw"></div>

                        </div>
                        <h1 style="margin-top:1rem">Votre compte a été créé avec succès !</h1>
                        <p>Vous pouvez désormais passer à l’étape suivante.</p>
                        <button class="submit-btn" type="submit">Continue</button>
                    </div>

                    <div class="confetti-container-animation">
                    </div>
                </div>


            </div>



            <script type="text/javascript" src="/mcm_website_theme/static/src/js/felicitations.js"></script>
        </t>
    </template>
</odoo>