<?xml version="1.0" encoding="UTF-8"?>
<odoo>
    <data>
        <template id="id_releve_note_print_report_pdf">
            <t t-call="web.html_container">
                <t t-foreach="docs" t-as="o">
                    <t t-call="web.basic_layout">
                        <style type="text/css">
                            .page {
                            line-height: 2 !important;
                            font-size:18px !important;
                            }
                        </style>
                        <t t-if="docs.note_exam_id">
                            <t t-foreach="docs.note_exam_id[-1]" t-as="res"
                               style="line-height:1.5;font-family:Montserrat;font-size:12%;page-break-before:always;">
                                <t t-if="res.resultat == 'recu'">
                                    <div class="page">
                                        <div class="oe_structure"/>
                                        <div class="row">
                                            <div class="col-12">
                                                <br></br>
                                                <img src='/partner_exam/static/src/img/new_reussite.png' height="260"
                                                     width="970"/>
                                                <br></br>
                                                Je soussigné <b>Nasserddine Cherih</b> agissant en tant que Directeur
                                                Général du
                                                centre de
                                                formation Digimoov, agréé par le préfet de la région Ile de France sous
                                                le
                                                numéro
                                                d'agrément 2019-0110, après délibération du Jury,
                                                <br/>
                                                Atteste que
                                                <strong>
                                                    <t t-foreach="docs" t-as="prenom"
                                                       style="line-height:1.5;font-family:Montserrat;font-size:12%;page-break-before:always;">
                                                        <span t-field="prenom.name"/>
                                                    </t>
                                                </strong>
                                                <br/>
                                                Né(e) le :
                                                <strong>
                                                    <t t-foreach="docs" t-as="birthday"
                                                       style="line-height:1.5;font-family:Montserrat;font-size:12%;page-break-before:always;">
                                                        <span t-field="birthday.birthday"/>
                                                    </t>
                                                </strong>
                                                <br/>
                                                Demeurant au :
                                                <strong>
                                                    <t t-foreach="docs" t-as="adresse"
                                                       style="line-height:1.5;font-family:Montserrat;font-size:12 %;page-break-before: always;">
                                                        <span t-field="adresse.street"/>,
                                                        <span t-field="adresse.zip"/>
                                                        <span t-field="adresse.city"/>
                                                    </t>
                                                </strong>
                                                <br></br>
                                                A été
                                                <strong>
                                                    <t t-if="docs.note_exam_id">
                                                        <t t-foreach="docs.note_exam_id[-1]" t-as="mention"
                                                           style="line-height:1.5;font-family:Montserrat;font-size:12 %;page-break-before: always;">
                                                            <t t-if="mention.mention == 'recu'">
                                                                <span>reçu(e)</span>
                                                            </t>
                                                            <t t-else=""></t>
                                                        </t>
                                                    </t>
                                                </strong>
                                                aux épreuves d’examen pour l’obtention de
                                                l’attestation de capacité de transport léger de marchandises
                                                organisé au centre d’examen situé au
                                                <strong>
                                                    <t t-if="docs.mcm_session_id">
                                                        <t t-foreach="docs.mcm_session_id" t-as="centre_examen"
                                                           style="line-height:1.5;font-family:Montserrat;font-size:12 %;page-break-before: always;">
                                                            <t t-if="centre_examen.adresse_examen">
                                                                <span t-esc="centre_examen.adresse_examen"/>
                                                            </t>
                                                        </t>
                                                    </t>
                                                </strong>
                                                <br></br>
                                                le
                                                <strong>
                                                    <t t-foreach="docs.mcm_session_id" t-as="le"
                                                       style="line-height:1.5;font-family:Montserrat;font-size:12 %;page-break-before: always;">
                                                        <t t-if="le.date_exam">
                                                            <span t-field="le.date_exam"
                                                                  t-field-options='{"format": "dd/MM/yyyy"}'/>
                                                        </t>
                                                    </t>
                                                </strong>
                                                pour son
                                                <strong>
                                                    <t t-if="docs.note_exam_id">
                                                        <t t-foreach="docs.note_exam_id[-1]" t-as="passage"
                                                           style="line-height:1.5;font-family:Montserrat;font-size:12%;page-break-before:always;">
                                                            <t t-if="passage.nombre_de_passage">
                                                                <span t-esc="passage.nombre_de_passage"/>
                                                            </t>
                                                        </t>
                                                    </t>
                                                </strong>
                                                passage, en ayant obtenu les notes
                                                suivantes :
                                                <img src='/partner_exam/static/src/img/text_1_2.png'
                                                     style="height:40px;width:840px;padding-left:50px;"/>
                                                <br></br>
                                                <p align="center">
                                                    <b>
                                                        Conformément à l’arrêté du 28 décembre 2011 relatif à la
                                                        délivrance des
                                                        attestations
                                                        de capacité, professionnelle
                                                        permettant l’exercice de la profession de transporteur public
                                                        routier, article 7
                                                    </b>
                                                </p>
                                                <div class="row" style="padding-top:5px!important;">
                                                    <div class="col-1"></div>
                                                    <div class="col-10">
                                                        <table class="table table-bordered"
                                                               style="border:1px solid black;">
                                                            <tr align="center">
                                                                <th>EPREUVES</th>
                                                                <th>NOTES/20</th>
                                                            </tr>
                                                            <tbody>
                                                                <tr>
                                                                    <td align="center">
                                                                        <b>EPREUVE A - QUESTIONS A CHOIX UNIQUE</b>
                                                                    </td>
                                                                    <td align="center">
                                                                        <strong>
                                                                            <t t-if="docs.note_exam_id">
                                                                                <t t-foreach="docs.note_exam_id[-1]"
                                                                                   t-as="a"
                                                                                   style="line-height:1.5;font-family:Montserrat;font-size:12%;page-break-before:always;">
                                                                                    <t t-if="a.epreuve_a &gt; 0">
                                                                                        <span t-esc="a.epreuve_a"/>
                                                                                    </t>
                                                                                    <t t-else="">
                                                                                        <span t-esc="Absent"/>
                                                                                    </t>
                                                                                </t>
                                                                            </t>
                                                                        </strong>
                                                                    </td>
                                                                </tr>
                                                                <tr>
                                                                    <td align="center">
                                                                        <b>EPREUVE B - QUESTION DE RÉDACTION</b>
                                                                    </td>
                                                                    <td align="center">
                                                                        <strong>
                                                                            <t t-if="docs.note_exam_id">
                                                                                <t t-foreach="docs.note_exam_id[-1]"
                                                                                   t-as="b"
                                                                                   style="line-height:1.5;font-family:Montserrat;font-size:12%;page-break-before:always;">
                                                                                    <t t-if="b.epreuve_b">
                                                                                        <span t-esc="b.epreuve_b"/>
                                                                                    </t>
                                                                                </t>
                                                                            </t>
                                                                        </strong>
                                                                    </td>
                                                                </tr>
                                                            </tbody>
                                                        </table>
                                                    </div>
                                                </div>

                                                <div class="row" style="padding-top:10px!important;">
                                                    <div class="col-1"></div>
                                                    <div class="col-10">
                                                        <table class="table table-bordered">
                                                            <tbody>
                                                                <tr>
                                                                    <td align="center">
                                                                        <b>Moyenne générale</b>
                                                                    </td>
                                                                    <td align="center">
                                                                        <strong>
                                                                            <t t-if="docs.note_exam_id">
                                                                                <t t-foreach="docs.note_exam_id[-1]"
                                                                                   t-as="moy_general"
                                                                                   style="line-height:1.5;font-family:Montserrat;font-size:12%;page-break-before:always;">
                                                                                    <t t-if="moy_general.moyenne_generale">
                                                                                        <span t-esc="moy_general.moyenne_generale"/>
                                                                                    </t>
                                                                                </t>
                                                                            </t>
                                                                        </strong>
                                                                    </td>
                                                                </tr>
                                                                <tr>
                                                                    <td align="center">
                                                                        <b>Résultat</b>
                                                                    </td>
                                                                    <td align="center">
                                                                        <strong>
                                                                            <t t-if="docs.note_exam_id">
                                                                                <t t-foreach="docs.note_exam_id[-1]"
                                                                                   t-as="res"
                                                                                   style="line-height:1.5;font-family:Montserrat;font-size:12%;page-break-before:always;">
                                                                                    <t t-if="res.resultat == 'recu'">
                                                                                        <b>Reçu(e)</b>
                                                                                    </t>
                                                                                    <t t-else=""></t>
                                                                                </t>
                                                                            </t>
                                                                        </strong>
                                                                    </td>
                                                                </tr>
                                                            </tbody>
                                                        </table>
                                                    </div>
                                                </div>
                                                <br></br>
                                                <p align="center">
                                                    <b>Il est rappelé que d’après l’arrêté du 28 décembre 2011 relatif à
                                                        la
                                                        délivrance des attestations de capacité
                                                        professionnelle permettant l'exercice de la profession de
                                                        transporteur
                                                        public routier, sont déclarés reçus
                                                        les candidats qui ont obtenu, pour l'ensemble des épreuves, une
                                                        note au
                                                        moins égale à 120 sur 200 soit
                                                        12/20, sous réserve qu'ils aient obtenu au moins 50 points soit
                                                        10/20
                                                        pour
                                                        le questionnaire à choix
                                                        multiples et 40 points soit 8/20 pour l'épreuve à réponses
                                                        rédigées.
                                                    </b>
                                                </p>
                                                <br></br>
                                                <div class="row" style="padding-left:100px!important;">
                                                    <table border="0" width="700">
                                                        <thead>
                                                            <tr align="center">
                                                                <th>Signature
                                                                    <img src='/partner_exam/static/src/img/signature.png'
                                                                         style="height:100px; width:200px;"/>
                                                                </th>
                                                                <th width="400"></th>
                                                                <th>À Paris,
                                                                    <span>le</span>
                                                                    <br/>
                                                                    <span t-field="o.note_exam_id[-1].date_today"
                                                                          t-field-options='{"format": "dd/MM/yyyy"}'/>
                                                                </th>
                                                            </tr>
                                                        </thead>
                                                    </table>
                                                </div>
                                                <br></br>
                                                <br></br>
                                                <img src='/partner_exam/static/src/img/footer_attestation_r.png'
                                                     height="150"
                                                     width="1000"/>
                                            </div>
                                        </div>
                                    </div>
                                </t>
                            </t>
                        </t>
                        <!--  This is the second Template if the last line added in the list of Examen(notes)= Ajourne or absent-->
                        <t t-if="docs.note_exam_id">
                            <!--  Using the foreach with [-1] to get the last line in list-->
                            <t t-foreach="docs.note_exam_id[-1]" t-as="res"
                               style="line-height:1.5;font-family:Montserrat;font-size:12%;page-break-before:always;">
                                <t t-if="not res.resultat == 'recu'">
                                    <style type="text/css">
                                        .page {
                                        line-height: 2 !important;
                                        }
                                    </style>
                                    <div class="page">
                                        <div class="row">
                                            <div class="col-12">
                                                <img src='/partner_exam/static/src/img/attestation_ajournement.png'
                                                     height="300"
                                                     width="970"/>
                                                <br></br>
                                                Je soussigné <b>Nasserddine Cherih</b> agissant en tant que Directeur
                                                Général du
                                                centre de
                                                formation Digimoov, agréé par le préfet de la région Ile de France sous
                                                le
                                                numéro
                                                d'agrément 2019-0110, après délibération du Jury,
                                                <br></br>

                                                Atteste que
                                                <strong>
                                                    <t t-foreach="docs" t-as="prenom"
                                                       style="line-height:1.5;font-family:Montserrat;font-size:12%;page-break-before:always;">
                                                        <span t-field="prenom.name"/>
                                                    </t>
                                                </strong>
                                                <br/>
                                                Né(e) le :
                                                <strong>
                                                    <t t-foreach="docs" t-as="birthday"
                                                       style="line-height:1.5;font-family:Montserrat;font-size:12%;page-break-before:always;">
                                                        <span t-field="birthday.birthday"/>
                                                    </t>
                                                </strong>
                                                <br/>
                                                Demeurant au :
                                                <strong>
                                                    <t t-foreach="docs" t-as="adresse"
                                                       style="line-height:1.5;font-family:Montserrat;font-size:12 %;page-break-before: always;">
                                                        <span t-field="adresse.street"/>,
                                                        <span></span>
                                                        <span t-field="adresse.zip"/>
                                                        <span t-field="adresse.city"/>
                                                    </t>
                                                </strong>
                                                <br></br>
                                                A été
                                                <strong>
                                                    <t t-if="docs.note_exam_id">
                                                        <t t-foreach="docs.note_exam_id[-1]" t-as="mention"
                                                           style="line-height:1.5;font-family:Montserrat;font-size:12 %;page-break-before: always;">
                                                            <t t-if="mention.mention">
                                                                <span t-field="mention.mention"/>(e)
                                                            </t>
                                                        </t>
                                                    </t>
                                                </strong>
                                                aux épreuves d’examen pour l’obtention de
                                                l’attestation de capacité de transport léger de marchandises
                                                organisé au centre d’examen situé au
                                                <strong>
                                                    <t t-if="docs.mcm_session_id">
                                                        <t t-foreach="docs.mcm_session_id" t-as="centre_examen"
                                                           style="line-height:1.5;font-family:Montserrat;font-size:12 %;page-break-before: always;">
                                                            <t t-if="centre_examen.adresse_examen">
                                                                <span t-esc="centre_examen.adresse_examen"/>
                                                            </t>
                                                        </t>
                                                    </t>
                                                </strong>
                                                <br></br>
                                                le
                                                <strong>
                                                    <t t-foreach="docs.mcm_session_id" t-as="le"
                                                       style="line-height:1.5;font-family:Montserrat;font-size:12 %;page-break-before: always;">
                                                        <t t-if="le.date_exam">
                                                            <span t-field="le.date_exam"
                                                                  t-field-options='{"format": "dd/MM/yyyy"}'/>
                                                        </t>
                                                    </t>
                                                </strong>
                                                pour son
                                                <strong>
                                                    <t t-if="docs.note_exam_id">
                                                        <t t-foreach="docs.note_exam_id[-1]" t-as="passage"
                                                           style="line-height:1.5;font-family:Montserrat;font-size:12%;page-break-before:always;">
                                                            <t t-if="passage.nombre_de_passage">
                                                                <span t-esc="passage.nombre_de_passage"/>
                                                            </t>
                                                        </t>
                                                    </t>
                                                </strong>
                                                passage, en ayant obtenu les notes
                                                suivantes :
                                                <img src='/partner_exam/static/src/img/text_1_2.png'
                                                     style="height:40px;width:840px;padding-left:50px;"/>
                                                <br></br>
                                                <p align="center">
                                                    <b>
                                                        Conformément à l’arrêté du 28 décembre 2011 relatif à la
                                                        délivrance des
                                                        attestations
                                                        de capacité, professionnelle
                                                        permettant l’exercice de la profession de transporteur public
                                                        routier, article 7
                                                    </b>
                                                </p>
                                                <div class="row" style="padding-top:5px!important;">
                                                    <div class="col-1"></div>
                                                    <div class="col-10">
                                                        <table class="table table-bordered"
                                                               style="border:1px solid black;">
                                                            <tr align="center">
                                                                <th>EPREUVES</th>
                                                                <th>NOTES/20</th>
                                                            </tr>
                                                            <tbody>
                                                                <tr>
                                                                    <td align="center">
                                                                        <b>EPREUVE A - QUESTIONS A CHOIX UNIQUE</b>
                                                                    </td>
                                                                    <td align="center">
                                                                        <strong>
                                                                            <t t-if="docs.note_exam_id">
                                                                                <t t-foreach="docs.note_exam_id[-1]"
                                                                                   t-as="a"
                                                                                   style="line-height:1.5;font-family:Montserrat;font-size:12%;page-break-before:always;">
                                                                                    <t t-if="a.epreuve_a &gt; 0">
                                                                                        <span t-esc="a.epreuve_a"/>
                                                                                    </t>
                                                                                    <t t-else="">
                                                                                        <span>Absent</span>
                                                                                    </t>
                                                                                </t>
                                                                            </t>
                                                                        </strong>
                                                                    </td>
                                                                </tr>
                                                                <tr>
                                                                    <td align="center">
                                                                        <b>EPREUVE B - QUESTION DE RÉDACTION</b>
                                                                    </td>
                                                                    <td align="center">
                                                                        <strong>
                                                                            <t t-if="docs.note_exam_id">
                                                                                <t t-foreach="docs.note_exam_id[-1]"
                                                                                   t-as="b"
                                                                                   style="line-height:1.5;font-family:Montserrat;font-size:12%;page-break-before:always;">
                                                                                    <t t-if="b.epreuve_b">
                                                                                        <span t-esc="b.epreuve_b"/>
                                                                                    </t>
                                                                                    <t t-else="">
                                                                                        <span>Absent</span>
                                                                                    </t>
                                                                                </t>
                                                                            </t>
                                                                        </strong>
                                                                    </td>
                                                                </tr>
                                                            </tbody>
                                                        </table>
                                                    </div>
                                                    <div class="col-1"></div>
                                                </div>

                                                <div class="row" style="padding-top:10px!important;">
                                                    <div class="col-1"></div>
                                                    <div class="col-10">
                                                        <table class="table table-bordered">
                                                            <tbody>
                                                                <tr>
                                                                    <td align="center">
                                                                        <b>Moyenne générale</b>
                                                                    </td>
                                                                    <td align="center">
                                                                        <strong>
                                                                            <t t-if="docs.note_exam_id">
                                                                                <t t-foreach="docs.note_exam_id[-1]"
                                                                                   t-as="moy_general"
                                                                                   style="line-height:1.5;font-family:Montserrat;font-size:12%;page-break-before:always;">
                                                                                    <t t-if="moy_general.moyenne_generale">
                                                                                        <span t-esc="moy_general.moyenne_generale"/>
                                                                                    </t>
                                                                                    <t t-else="">
                                                                                        <span>Absent</span>
                                                                                    </t>
                                                                                </t>
                                                                            </t>
                                                                        </strong>
                                                                    </td>
                                                                </tr>
                                                                <tr>
                                                                    <td align="center">
                                                                        <b>Résultat</b>
                                                                    </td>
                                                                    <td align="center">
                                                                        <strong>
                                                                            <t t-if="docs.note_exam_id">
                                                                                <t t-foreach="docs.note_exam_id[-1]"
                                                                                   t-as="res"
                                                                                   style="line-height:1.5;font-family:Montserrat;font-size:12%;page-break-before:always;">
                                                                                    <t t-if="res.resultat == 'ajourne'">
                                                                                        <b>Ajourné(e)</b>
                                                                                    </t>
                                                                                    <t t-else=""></t>
                                                                                </t>
                                                                            </t>
                                                                        </strong>
                                                                    </td>
                                                                </tr>
                                                            </tbody>
                                                        </table>
                                                    </div>
                                                    <div class="col-1"></div>
                                                </div>
                                                <br></br>
                                                <center>
                                                    <b>Il est rappelé que d’après l’arrêté du 28 décembre 2011 relatif à
                                                        la
                                                        délivrance des attestations de capacité
                                                        professionnelle permettant l'exercice de la profession de
                                                        transporteur
                                                        public routier, sont déclarés reçus
                                                        les candidats qui ont obtenu, pour l'ensemble des épreuves, une
                                                        note au
                                                        moins égale à 120 sur 200 soit
                                                        12/20, sous réserve qu'ils aient obtenu au moins 50 points soit
                                                        10/20 pour
                                                        le questionnaire à choix
                                                        multiples et 40 points soit 8/20 pour l'épreuve à réponses
                                                        rédigées.
                                                    </b>
                                                </center>
                                                <br></br>
                                                <div class="row" style="padding-left:100px!important;">
                                                    <table border="0" width="700">
                                                        <thead>
                                                            <tr align="center">
                                                                <th>Signature
                                                                    <img src='/partner_exam/static/src/img/signature.png'
                                                                         style="height:100px; width:200px;"/>
                                                                </th>
                                                                <th width="400"></th>
                                                                <th>À Paris,
                                                                    <span>le</span>
                                                                    <br/>
                                                                    <span t-field="o.note_exam_id[-1].date_today"
                                                                          t-field-options='{"format": "dd/MM/yyyy"}'/>
                                                                </th>
                                                            </tr>
                                                        </thead>
                                                    </table>
                                                </div>
                                                <br></br>
                                                <br></br>
                                                <img src='/partner_exam/static/src/img/footer_attestation_r.png'
                                                     height="150"
                                                     width="1000"/>
                                            </div>
                                        </div>
                                    </div>
                                </t>
                            </t>
                        </t>
                    </t>
                </t>
            </t>
        </template>
    </data>
</odoo>